{
  "db_name": "PostgreSQL",
  "query": "SELECT id, developer_user_id FROM developer_teams\n           WHERE LOWER(public_slug) = LOWER($1) AND status = 'active'",
  "describe": {
    "columns": [
      {
        "ordinal": 0,
        "name": "id",
        "type_info": "Uuid"
      },
      {
        "ordinal": 1,
        "name": "developer_user_id",
        "type_info": "Uuid"
      }
    ],
    "parameters": {
      "Left": [
        "Text"
      ]
    },
    "nullable": [
      false,
      false
    ]
  },
  "hash": "49a37eb3cafe84bf49c9accd06f7e6e62db3783708f6f805be060a3d58e51b6b"
}
