{
  "db_name": "PostgreSQL",
  "query": "\n                SELECT \n                    (SELECT COALESCE(SUM(balance_cents), 0)::bigint FROM wallets WHERE wallet_type = 'cash' AND currency = 'USD') as total_wallets,\n                    (SELECT COALESCE(SUM(amount_cents), 0)::bigint FROM deposit_requests WHERE status IN ('approved', 'completed') AND currency = 'USD') as total_deposits,\n                    (SELECT COALESCE(SUM(amount_cents), 0)::bigint FROM withdrawal_requests WHERE status != 'rejected' AND currency = 'USD') as total_withdrawals,\n                    (SELECT COALESCE(SUM(total_cents), 0)::bigint FROM orders WHERE status IN ('completed', 'pending_kyc')) as total_purchases\n                ",
  "describe": {
    "columns": [
      {
        "ordinal": 0,
        "name": "total_wallets",
        "type_info": "Int8"
      },
      {
        "ordinal": 1,
        "name": "total_deposits",
        "type_info": "Int8"
      },
      {
        "ordinal": 2,
        "name": "total_withdrawals",
        "type_info": "Int8"
      },
      {
        "ordinal": 3,
        "name": "total_purchases",
        "type_info": "Int8"
      }
    ],
    "parameters": {
      "Left": []
    },
    "nullable": [
      null,
      null,
      null,
      null
    ]
  },
  "hash": "f0656773a93aef4c1f7c8d1ceb8a61186b8b75df13921599792a12b1d2398840"
}
