{
  "db_name": "PostgreSQL",
  "query": "INSERT INTO affiliate_links\n              (code, link_type, attribution_user_id, payout_user_id, status)\n           VALUES ($1, 'personal', $2, $2, 'active') RETURNING id",
  "describe": {
    "columns": [
      {
        "ordinal": 0,
        "name": "id",
        "type_info": "Uuid"
      }
    ],
    "parameters": {
      "Left": [
        "Varchar",
        "Uuid"
      ]
    },
    "nullable": [
      false
    ]
  },
  "hash": "589a76107dd7b4b33f3f2ae1d3fb27fd9aa18a1193d85be7f26b3edbbbb6f894"
}
