{
  "db_name": "PostgreSQL",
  "query": "SELECT attribution_user_id, payout_user_id\n         FROM affiliate_referrals WHERE referred_user_id = $1",
  "describe": {
    "columns": [
      {
        "ordinal": 0,
        "name": "attribution_user_id",
        "type_info": "Uuid"
      },
      {
        "ordinal": 1,
        "name": "payout_user_id",
        "type_info": "Uuid"
      }
    ],
    "parameters": {
      "Left": [
        "Uuid"
      ]
    },
    "nullable": [
      false,
      false
    ]
  },
  "hash": "9f07a333edde670442caaaa68bfaba0cfef301da061dff06aa9fd61523e05e76"
}
